README.md
setup.py
TOPSIS_Karan_101803135/__init__.py
TOPSIS_Karan_101803135/topsis.py
TOPSIS_Karan_101803135.egg-info/PKG-INFO
TOPSIS_Karan_101803135.egg-info/SOURCES.txt
TOPSIS_Karan_101803135.egg-info/dependency_links.txt
TOPSIS_Karan_101803135.egg-info/requires.txt
TOPSIS_Karan_101803135.egg-info/top_level.txt