Metadata-Version: 2.1
Name: TOPSIS-Karan-101803135
Version: 0.6
Summary: A python package for Multiple Criteria Decision Making (MCDM) using Topsis
Home-page: https://github.com/karangoyal7/TOPSIS-Karan-101803135
Author: Karan Goyal
Author-email: karandps7@gmail.com
License: MIT
Download-URL: https://github.com/karangoyal7/TOPSIS-Karan-101803135/archive/v0.6.tar.gz
Keywords: TOPSIS,101803135,Karan Goyal
Platform: UNKNOWN
Classifier: Development Status :: 3 - Alpha
Classifier: Intended Audience :: Developers
Classifier: Topic :: Software Development :: Build Tools
Classifier: License :: OSI Approved :: MIT License
Classifier: Programming Language :: Python :: 3
Classifier: Programming Language :: Python :: 3.4
Classifier: Programming Language :: Python :: 3.5
Classifier: Programming Language :: Python :: 3.6
Classifier: Programming Language :: Python :: 3.7
Classifier: Programming Language :: Python :: 3.8
